src/__init__.py
src/main.py
tests/__init__.py
tests/test_calculations.py
gradescalculator-2.0.2.dist-info/METADATA
gradescalculator-2.0.2.dist-info/WHEEL
gradescalculator-2.0.2.dist-info/entry_points.txt
gradescalculator-2.0.2.dist-info/top_level.txt
gradescalculator-2.0.2.dist-info/RECORD
