Metadata-Version: 2.1
Name: gradescalculator
Version: 2.0.2
Summary: Un package pour calculer des notes avec des poids différents.
Home-page: https://github.com/BERTHETquentin/GradesCalculator
Author: Quentin Berthet
Author-email: quentin@berthet.ch
License: UNKNOWN
Platform: UNKNOWN
Classifier: Programming Language :: Python :: 3
Classifier: License :: OSI Approved :: MIT License
Classifier: Operating System :: OS Independent
Requires-Python: >=3.6
